planqk/__init__.py
planqk/mcp/__init__.py
planqk/mcp/kipu_services.txt
planqk/mcp/main.py
platform_mcp_server-0.0.6.dist-info/METADATA
platform_mcp_server-0.0.6.dist-info/WHEEL
platform_mcp_server-0.0.6.dist-info/entry_points.txt
platform_mcp_server-0.0.6.dist-info/top_level.txt
platform_mcp_server-0.0.6.dist-info/RECORD
