Metadata-Version: 2.4
Name: platform-mcp-server
Version: 0.0.6
Summary: Platform MCP Server
Requires-Python: >=3.11
Requires-Dist: httpx>=0.28.1
Requires-Dist: mcp[cli]>=1.6.0
